{"v":"4.8.0","meta":{"g":"LottieFiles AE 3.1.1","a":"Sadjad","k":"Dislike","d":"Uicon Animated Icons","tc":""},"fr":30,"ip":0,"op":56,"w":128,"h":128,"nm":"Dislike_lottie","ddd":0,"assets":[],"layers":[{"ddd":0,"ind":1,"ty":3,"nm":"Null 1","sr":1,"ks":{"o":{"a":0,"k":0,"ix":11},"r":{"a":1,"k":[{"i":{"x":[0.4],"y":[1]},"o":{"x":[0.6],"y":[0]},"t":9,"s":[0]},{"i":{"x":[0.4],"y":[1]},"o":{"x":[0.6],"y":[0]},"t":23,"s":[-21]},{"i":{"x":[0.4],"y":[1]},"o":{"x":[0.6],"y":[0]},"t":37,"s":[15]},{"t":46,"s":[0]}],"ix":10},"p":{"a":0,"k":[36.75,55.5,0],"ix":2},"a":{"a":0,"k":[0,0,0],"ix":1},"s":{"a":0,"k":[100,100,100],"ix":6}},"ao":0,"ip":0,"op":241,"st":0,"bm":0},{"ddd":0,"ind":2,"ty":4,"nm":"Layer 1 Outlines","parent":1,"sr":1,"ks":{"o":{"a":0,"k":100,"ix":11},"r":{"a":0,"k":0,"ix":10},"p":{"a":0,"k":[27.076,10.729,0],"ix":2},"a":{"a":0,"k":[63.826,66.229,0],"ix":1},"s":{"a":0,"k":[100,100,100],"ix":6}},"ao":0,"shapes":[{"ty":"gr","it":[{"ind":0,"ty":"sh","ix":1,"ks":{"a":1,"k":[{"i":{"x":0.2,"y":1},"o":{"x":0.8,"y":0},"t":9,"s":[{"i":[[0,0],[0,0]],"o":[[0,0],[0,0]],"v":[[37,47],[37,51.5]],"c":false}]},{"i":{"x":0.2,"y":1},"o":{"x":0.8,"y":0},"t":23,"s":[{"i":[[0,0],[0,0]],"o":[[0,0],[0,0]],"v":[[37,55.75],[37,60.25]],"c":false}]},{"t":37,"s":[{"i":[[0,0],[0,0]],"o":[[0,0],[0,0]],"v":[[37,47],[37,51.5]],"c":false}]}],"ix":2},"nm":"Path 1","mn":"ADBE Vector Shape - Group","hd":false},{"ty":"st","c":{"a":0,"k":[0,0,0,1],"ix":3},"o":{"a":0,"k":100,"ix":4},"w":{"a":0,"k":5,"ix":5},"lc":2,"lj":2,"bm":0,"nm":"Stroke 1","mn":"ADBE Vector Graphic - Stroke","hd":false},{"ty":"tr","p":{"a":0,"k":[0,0],"ix":2},"a":{"a":0,"k":[0,0],"ix":1},"s":{"a":0,"k":[100,100],"ix":3},"r":{"a":0,"k":0,"ix":6},"o":{"a":0,"k":100,"ix":7},"sk":{"a":0,"k":0,"ix":4},"sa":{"a":0,"k":0,"ix":5},"nm":"Transform"}],"nm":"Group 1","np":2,"cix":2,"bm":0,"ix":1,"mn":"ADBE Vector Group","hd":false},{"ty":"gr","it":[{"ind":0,"ty":"sh","ix":1,"ks":{"a":0,"k":{"i":[[0,0],[0,0],[0,4.418],[0,0],[-4.418,0],[0,0]],"o":[[0,0],[-4.418,0],[0,0],[0,-4.418],[0,0],[0,0]],"v":[[-16.766,7.749],[-30.266,7.749],[-38.266,-0.251],[-38.266,-25.251],[-30.266,-33.251],[-16.766,-33.251]],"c":false},"ix":2},"nm":"Path 1","mn":"ADBE Vector Shape - Group","hd":false},{"ind":1,"ty":"sh","ix":2,"ks":{"a":1,"k":[{"i":{"x":0.2,"y":1},"o":{"x":0.8,"y":0},"t":9,"s":[{"i":[[0,0],[0,0],[3.17,8.5],[-5.531,0],[0,0],[1.042,5.341],[0,0],[6.389,0],[0,0]],"o":[[0,0],[5.578,7.153],[-1.932,-5.182],[0,0],[5.441,0],[0,0],[-1.223,-6.271],[0,0],[0,0]],"v":[[-16.766,7.749],[-2.461,26.098],[11.225,18.45],[18.656,7.749],[28.734,7.749],[37.223,-2.557],[33.34,-22.455],[20.234,-33.251],[-16.766,-33.251]],"c":false}]},{"i":{"x":0.2,"y":1},"o":{"x":0.8,"y":0},"t":23,"s":[{"i":[[0,0],[0,0],[9.01,0.299],[-5.531,0],[0,0],[1.042,5.341],[0,0],[6.389,0],[0,0]],"o":[[0,0],[18.07,4.026],[-11.286,-0.375],[0,0],[5.441,0],[0,0],[-1.223,-6.271],[0,0],[0,0]],"v":[[-16.766,7.749],[7.039,18.223],[20.725,7.7],[18.656,7.749],[28.734,7.749],[37.223,-2.557],[33.34,-22.455],[20.234,-33.251],[-16.766,-33.251]],"c":false}]},{"i":{"x":0.2,"y":1},"o":{"x":0.8,"y":0},"t":37,"s":[{"i":[[0,0],[0,0],[1.665,9.477],[-5.531,0],[0,0],[1.042,5.341],[0,0],[6.389,0],[0,0]],"o":[[0,0],[1.862,7.514],[-0.957,-5.447],[0,0],[5.441,0],[0,0],[-1.223,-6.271],[0,0],[0,0]],"v":[[-16.766,7.749],[-9.511,28.764],[4.174,21.116],[18.656,7.749],[28.734,7.749],[37.223,-2.557],[33.34,-22.455],[20.234,-33.251],[-16.766,-33.251]],"c":false}]},{"t":46,"s":[{"i":[[0,0],[0,0],[3.17,8.5],[-5.531,0],[0,0],[1.042,5.341],[0,0],[6.389,0],[0,0]],"o":[[0,0],[5.578,7.153],[-1.932,-5.182],[0,0],[5.441,0],[0,0],[-1.223,-6.271],[0,0],[0,0]],"v":[[-16.766,7.749],[-2.461,26.098],[11.225,18.45],[18.656,7.749],[28.734,7.749],[37.223,-2.557],[33.34,-22.455],[20.234,-33.251],[-16.766,-33.251]],"c":false}]}],"ix":2},"nm":"Path 2","mn":"ADBE Vector Shape - Group","hd":false},{"ind":2,"ty":"sh","ix":3,"ks":{"a":0,"k":{"i":[[0,0],[0,0]],"o":[[0,0],[0,0]],"v":[[-16.766,7.749],[-16.766,-33.251]],"c":false},"ix":2},"nm":"Path 3","mn":"ADBE Vector Shape - Group","hd":false},{"ty":"mm","mm":1,"nm":"Merge Paths 1","mn":"ADBE Vector Filter - Merge","hd":false},{"ty":"st","c":{"a":0,"k":[0,0,0,1],"ix":3},"o":{"a":0,"k":100,"ix":4},"w":{"a":0,"k":5,"ix":5},"lc":1,"lj":1,"ml":4,"bm":0,"nm":"Stroke 1","mn":"ADBE Vector Graphic - Stroke","hd":false},{"ty":"tr","p":{"a":0,"k":[64.266,68.251],"ix":2},"a":{"a":0,"k":[0,0],"ix":1},"s":{"a":0,"k":[100,100],"ix":3},"r":{"a":0,"k":0,"ix":6},"o":{"a":0,"k":100,"ix":7},"sk":{"a":0,"k":0,"ix":4},"sa":{"a":0,"k":0,"ix":5},"nm":"Transform"}],"nm":"Group 2","np":5,"cix":2,"bm":0,"ix":2,"mn":"ADBE Vector Group","hd":false}],"ip":0,"op":241,"st":0,"bm":0}],"markers":[]}