{"v":"4.8.0","meta":{"g":"LottieFiles AE 3.1.1","a":"Sadjad","k":"Grid","d":"Uicon Animated Icons","tc":""},"fr":30,"ip":0,"op":58,"w":128,"h":128,"nm":"Grid_lottie","ddd":0,"assets":[],"layers":[{"ddd":0,"ind":1,"ty":3,"nm":"Null 1","sr":1,"ks":{"o":{"a":0,"k":0,"ix":11},"r":{"a":0,"k":0,"ix":10},"p":{"a":0,"k":[64,64,0],"ix":2},"a":{"a":0,"k":[0,0,0],"ix":1},"s":{"a":1,"k":[{"i":{"x":[0,0,0],"y":[1,1,1]},"o":{"x":[1,1,1],"y":[0,0,0]},"t":9,"s":[100,100,100]},{"i":{"x":[0,0,0],"y":[1,1,1]},"o":{"x":[1,1,1],"y":[0,0,0]},"t":25,"s":[90,90,100]},{"t":48,"s":[100,100,100]}],"ix":6}},"ao":0,"ip":0,"op":241,"st":0,"bm":0},{"ddd":0,"ind":2,"ty":4,"nm":"rect Outlines","parent":1,"sr":1,"ks":{"o":{"a":0,"k":100,"ix":11},"r":{"a":0,"k":0,"ix":10},"p":{"a":0,"k":[0,0,0],"ix":2},"a":{"a":0,"k":[64,64,0],"ix":1},"s":{"a":0,"k":[100,100,100],"ix":6}},"ao":0,"shapes":[{"ty":"gr","it":[{"ind":0,"ty":"sh","ix":1,"ks":{"a":0,"k":{"i":[[0,0],[-14.359,0],[0,0],[0,-14.359],[0,0],[14.359,0],[0,0],[0,14.359]],"o":[[0,-14.359],[0,0],[14.359,0],[0,0],[0,14.359],[0,0],[-14.359,0],[0,0]],"v":[[-38,-12],[-12,-38],[12,-38],[38,-12],[38,12],[12,38],[-12,38],[-38,12]],"c":true},"ix":2},"nm":"Path 1","mn":"ADBE Vector Shape - Group","hd":false},{"ty":"st","c":{"a":0,"k":[0,0,0,1],"ix":3},"o":{"a":0,"k":100,"ix":4},"w":{"a":0,"k":5,"ix":5},"lc":2,"lj":1,"ml":4,"bm":0,"nm":"Stroke 1","mn":"ADBE Vector Graphic - Stroke","hd":false},{"ty":"tr","p":{"a":0,"k":[64,64],"ix":2},"a":{"a":0,"k":[0,0],"ix":1},"s":{"a":0,"k":[100,100],"ix":3},"r":{"a":0,"k":0,"ix":6},"o":{"a":0,"k":100,"ix":7},"sk":{"a":0,"k":0,"ix":4},"sa":{"a":0,"k":0,"ix":5},"nm":"Transform"}],"nm":"Group 1","np":2,"cix":2,"bm":0,"ix":1,"mn":"ADBE Vector Group","hd":false}],"ip":0,"op":241,"st":0,"bm":0},{"ddd":0,"ind":3,"ty":4,"nm":"mask","parent":1,"td":1,"sr":1,"ks":{"o":{"a":0,"k":100,"ix":11},"r":{"a":0,"k":0,"ix":10},"p":{"a":0,"k":[0,0,0],"ix":2},"a":{"a":0,"k":[64,64,0],"ix":1},"s":{"a":0,"k":[100,100,100],"ix":6}},"ao":0,"shapes":[{"ty":"gr","it":[{"ind":0,"ty":"sh","ix":1,"ks":{"a":0,"k":{"i":[[0,0],[-14.359,0],[0,0],[0,-14.359],[0,0],[14.359,0],[0,0],[0,14.359]],"o":[[0,-14.359],[0,0],[14.359,0],[0,0],[0,14.359],[0,0],[-14.359,0],[0,0]],"v":[[-38,-12],[-12,-38],[12,-38],[38,-12],[38,12],[12,38],[-12,38],[-38,12]],"c":true},"ix":2},"nm":"Path 1","mn":"ADBE Vector Shape - Group","hd":false},{"ty":"fl","c":{"a":0,"k":[0,0,0,1],"ix":4},"o":{"a":0,"k":100,"ix":5},"r":1,"bm":0,"nm":"Fill 1","mn":"ADBE Vector Graphic - Fill","hd":false},{"ty":"tr","p":{"a":0,"k":[64,64],"ix":2},"a":{"a":0,"k":[0,0],"ix":1},"s":{"a":0,"k":[100,100],"ix":3},"r":{"a":0,"k":0,"ix":6},"o":{"a":0,"k":100,"ix":7},"sk":{"a":0,"k":0,"ix":4},"sa":{"a":0,"k":0,"ix":5},"nm":"Transform"}],"nm":"Group 1","np":2,"cix":2,"bm":0,"ix":1,"mn":"ADBE Vector Group","hd":false}],"ip":0,"op":241,"st":0,"bm":0},{"ddd":0,"ind":4,"ty":4,"nm":"grid Outlines 2","parent":1,"tt":1,"sr":1,"ks":{"o":{"a":0,"k":100,"ix":11},"r":{"a":0,"k":0,"ix":10},"p":{"a":0,"k":[0,0,0],"ix":2},"a":{"a":0,"k":[64,64,0],"ix":1},"s":{"a":1,"k":[{"i":{"x":[0.2,0.2,0.2],"y":[1,1,1]},"o":{"x":[0.8,0.8,0.8],"y":[0,0,0]},"t":9,"s":[100,100,100]},{"i":{"x":[0.2,0.2,0.2],"y":[1,1,1]},"o":{"x":[0.8,0.8,0.8],"y":[0,0,0]},"t":25,"s":[80,80,100]},{"t":48,"s":[100,100,100]}],"ix":6}},"ao":0,"shapes":[{"ty":"gr","it":[{"ind":0,"ty":"sh","ix":1,"ks":{"a":1,"k":[{"i":{"x":0.2,"y":1},"o":{"x":0.8,"y":0},"t":9,"s":[{"i":[[0,0],[0,0]],"o":[[0,0],[0,0]],"v":[[100,106],[28,106]],"c":false}]},{"i":{"x":0.2,"y":1},"o":{"x":0.8,"y":0},"t":25,"s":[{"i":[[0,0],[0,0]],"o":[[0,0],[0,0]],"v":[[100.965,98.57],[28.111,98.688]],"c":false}]},{"t":48,"s":[{"i":[[0,0],[0,0]],"o":[[0,0],[0,0]],"v":[[100,107.25],[28,107.25]],"c":false}]}],"ix":2},"nm":"Path 1","mn":"ADBE Vector Shape - Group","hd":false},{"ty":"st","c":{"a":0,"k":[0,0,0,1],"ix":3},"o":{"a":0,"k":100,"ix":4},"w":{"a":0,"k":5,"ix":5},"lc":2,"lj":2,"bm":0,"nm":"Stroke 1","mn":"ADBE Vector Graphic - Stroke","hd":false},{"ty":"tr","p":{"a":0,"k":[0,0],"ix":2},"a":{"a":0,"k":[0,0],"ix":1},"s":{"a":0,"k":[100,100],"ix":3},"r":{"a":0,"k":0,"ix":6},"o":{"a":0,"k":100,"ix":7},"sk":{"a":0,"k":0,"ix":4},"sa":{"a":0,"k":0,"ix":5},"nm":"Transform"}],"nm":"Group 1","np":2,"cix":2,"bm":0,"ix":1,"mn":"ADBE Vector Group","hd":false},{"ty":"gr","it":[{"ind":0,"ty":"sh","ix":1,"ks":{"a":1,"k":[{"i":{"x":0.2,"y":1},"o":{"x":0.8,"y":0},"t":9,"s":[{"i":[[0,0],[0,0]],"o":[[0,0],[0,0]],"v":[[107,28],[107,100]],"c":false}]},{"i":{"x":0.2,"y":1},"o":{"x":0.8,"y":0},"t":25,"s":[{"i":[[0,0],[0,0]],"o":[[0,0],[0,0]],"v":[[102.021,29.06],[102.139,98.688]],"c":false}]},{"t":48,"s":[{"i":[[0,0],[0,0]],"o":[[0,0],[0,0]],"v":[[108,28],[108,100]],"c":false}]}],"ix":2},"nm":"Path 1","mn":"ADBE Vector Shape - Group","hd":false},{"ty":"st","c":{"a":0,"k":[0,0,0,1],"ix":3},"o":{"a":0,"k":100,"ix":4},"w":{"a":0,"k":5,"ix":5},"lc":2,"lj":2,"bm":0,"nm":"Stroke 2","mn":"ADBE Vector Graphic - Stroke","hd":false},{"ty":"st","c":{"a":0,"k":[0,0,0,1],"ix":3},"o":{"a":0,"k":100,"ix":4},"w":{"a":0,"k":5,"ix":5},"lc":2,"lj":2,"bm":0,"nm":"Stroke 1","mn":"ADBE Vector Graphic - Stroke","hd":false},{"ty":"tr","p":{"a":0,"k":[0,0],"ix":2},"a":{"a":0,"k":[0,0],"ix":1},"s":{"a":0,"k":[100,100],"ix":3},"r":{"a":0,"k":0,"ix":6},"o":{"a":0,"k":100,"ix":7},"sk":{"a":0,"k":0,"ix":4},"sa":{"a":0,"k":0,"ix":5},"nm":"Transform"}],"nm":"Group 2","np":3,"cix":2,"bm":0,"ix":2,"mn":"ADBE Vector Group","hd":false},{"ty":"gr","it":[{"ind":0,"ty":"sh","ix":1,"ks":{"a":1,"k":[{"i":{"x":0.2,"y":1},"o":{"x":0.8,"y":0},"t":9,"s":[{"i":[[0,0],[0,0]],"o":[[0,0],[0,0]],"v":[[100,21.75],[28,21.75]],"c":false}]},{"i":{"x":0.2,"y":1},"o":{"x":0.8,"y":0},"t":25,"s":[{"i":[[0,0],[0,0]],"o":[[0,0],[0,0]],"v":[[100.262,28.062],[28.287,28.18]],"c":false}]},{"t":48,"s":[{"i":[[0,0],[0,0]],"o":[[0,0],[0,0]],"v":[[100,19.75],[28,19.75]],"c":false}]}],"ix":2},"nm":"Path 1","mn":"ADBE Vector Shape - Group","hd":false},{"ty":"st","c":{"a":0,"k":[0,0,0,1],"ix":3},"o":{"a":0,"k":100,"ix":4},"w":{"a":0,"k":5,"ix":5},"lc":2,"lj":2,"bm":0,"nm":"Stroke 1","mn":"ADBE Vector Graphic - Stroke","hd":false},{"ty":"tr","p":{"a":0,"k":[0,0],"ix":2},"a":{"a":0,"k":[0,0],"ix":1},"s":{"a":0,"k":[100,100],"ix":3},"r":{"a":0,"k":0,"ix":6},"o":{"a":0,"k":100,"ix":7},"sk":{"a":0,"k":0,"ix":4},"sa":{"a":0,"k":0,"ix":5},"nm":"Transform"}],"nm":"Group 3","np":2,"cix":2,"bm":0,"ix":3,"mn":"ADBE Vector Group","hd":false},{"ty":"gr","it":[{"ind":0,"ty":"sh","ix":1,"ks":{"a":1,"k":[{"i":{"x":0.2,"y":1},"o":{"x":0.8,"y":0},"t":9,"s":[{"i":[[0,0],[0,0]],"o":[[0,0],[0,0]],"v":[[23.75,28],[23.75,100]],"c":false}]},{"i":{"x":0.2,"y":1},"o":{"x":0.8,"y":0},"t":25,"s":[{"i":[[0,0],[0,0]],"o":[[0,0],[0,0]],"v":[[28.581,29.06],[28.698,97.808]],"c":false}]},{"t":48,"s":[{"i":[[0,0],[0,0]],"o":[[0,0],[0,0]],"v":[[20,28],[20,100]],"c":false}]}],"ix":2},"nm":"Path 1","mn":"ADBE Vector Shape - Group","hd":false},{"ty":"st","c":{"a":0,"k":[0,0,0,1],"ix":3},"o":{"a":0,"k":100,"ix":4},"w":{"a":0,"k":5,"ix":5},"lc":2,"lj":2,"bm":0,"nm":"Stroke 1","mn":"ADBE Vector Graphic - Stroke","hd":false},{"ty":"tr","p":{"a":0,"k":[0,0],"ix":2},"a":{"a":0,"k":[0,0],"ix":1},"s":{"a":0,"k":[100,100],"ix":3},"r":{"a":0,"k":0,"ix":6},"o":{"a":0,"k":100,"ix":7},"sk":{"a":0,"k":0,"ix":4},"sa":{"a":0,"k":0,"ix":5},"nm":"Transform"}],"nm":"Group 4","np":2,"cix":2,"bm":0,"ix":4,"mn":"ADBE Vector Group","hd":false}],"ip":0,"op":241,"st":0,"bm":0},{"ddd":0,"ind":5,"ty":4,"nm":"grid Outlines","parent":1,"sr":1,"ks":{"o":{"a":0,"k":100,"ix":11},"r":{"a":0,"k":0,"ix":10},"p":{"a":0,"k":[0,0,0],"ix":2},"a":{"a":0,"k":[64,64,0],"ix":1},"s":{"a":1,"k":[{"i":{"x":[0.2,0.2,0.2],"y":[1,1,1]},"o":{"x":[0.8,0.8,0.8],"y":[0,0,0]},"t":9,"s":[100,100,100]},{"i":{"x":[0.2,0.2,0.2],"y":[1,1,1]},"o":{"x":[0.8,0.8,0.8],"y":[0,0,0]},"t":25,"s":[75,75,100]},{"t":48,"s":[100,100,100]}],"ix":6}},"ao":0,"shapes":[{"ty":"gr","it":[{"ind":0,"ty":"sh","ix":1,"ks":{"a":1,"k":[{"i":{"x":0.2,"y":1},"o":{"x":0.8,"y":0},"t":9,"s":[{"i":[[0,0],[0,0]],"o":[[0,0],[0,0]],"v":[[100,77],[28,77]],"c":false}]},{"i":{"x":0.2,"y":1},"o":{"x":0.8,"y":0},"t":25,"s":[{"i":[[0,0],[0,0]],"o":[[0,0],[0,0]],"v":[[110.625,76.875],[17.688,76.875]],"c":false}]},{"t":48,"s":[{"i":[[0,0],[0,0]],"o":[[0,0],[0,0]],"v":[[100,77],[28,77]],"c":false}]}],"ix":2},"nm":"Path 1","mn":"ADBE Vector Shape - Group","hd":false},{"ty":"st","c":{"a":0,"k":[0,0,0,1],"ix":3},"o":{"a":0,"k":100,"ix":4},"w":{"a":0,"k":5,"ix":5},"lc":2,"lj":2,"bm":0,"nm":"Stroke 1","mn":"ADBE Vector Graphic - Stroke","hd":false},{"ty":"tr","p":{"a":0,"k":[0,0],"ix":2},"a":{"a":0,"k":[0,0],"ix":1},"s":{"a":0,"k":[100,100],"ix":3},"r":{"a":0,"k":0,"ix":6},"o":{"a":0,"k":100,"ix":7},"sk":{"a":0,"k":0,"ix":4},"sa":{"a":0,"k":0,"ix":5},"nm":"Transform"}],"nm":"Group 1","np":2,"cix":2,"bm":0,"ix":1,"mn":"ADBE Vector Group","hd":false},{"ty":"gr","it":[{"ind":0,"ty":"sh","ix":1,"ks":{"a":1,"k":[{"i":{"x":0.2,"y":1},"o":{"x":0.8,"y":0},"t":9,"s":[{"i":[[0,0],[0,0]],"o":[[0,0],[0,0]],"v":[[77,28],[77,100]],"c":false}]},{"i":{"x":0.2,"y":1},"o":{"x":0.8,"y":0},"t":25,"s":[{"i":[[0,0],[0,0]],"o":[[0,0],[0,0]],"v":[[76.875,17.688],[76.875,111.562]],"c":false}]},{"t":48,"s":[{"i":[[0,0],[0,0]],"o":[[0,0],[0,0]],"v":[[77,28],[77,100]],"c":false}]}],"ix":2},"nm":"Path 1","mn":"ADBE Vector Shape - Group","hd":false},{"ty":"st","c":{"a":0,"k":[0,0,0,1],"ix":3},"o":{"a":0,"k":100,"ix":4},"w":{"a":0,"k":5,"ix":5},"lc":2,"lj":2,"bm":0,"nm":"Stroke 2","mn":"ADBE Vector Graphic - Stroke","hd":false},{"ty":"st","c":{"a":0,"k":[0,0,0,1],"ix":3},"o":{"a":0,"k":100,"ix":4},"w":{"a":0,"k":5,"ix":5},"lc":2,"lj":2,"bm":0,"nm":"Stroke 1","mn":"ADBE Vector Graphic - Stroke","hd":false},{"ty":"tr","p":{"a":0,"k":[0,0],"ix":2},"a":{"a":0,"k":[0,0],"ix":1},"s":{"a":0,"k":[100,100],"ix":3},"r":{"a":0,"k":0,"ix":6},"o":{"a":0,"k":100,"ix":7},"sk":{"a":0,"k":0,"ix":4},"sa":{"a":0,"k":0,"ix":5},"nm":"Transform"}],"nm":"Group 2","np":3,"cix":2,"bm":0,"ix":2,"mn":"ADBE Vector Group","hd":false},{"ty":"gr","it":[{"ind":0,"ty":"sh","ix":1,"ks":{"a":1,"k":[{"i":{"x":0.2,"y":1},"o":{"x":0.8,"y":0},"t":9,"s":[{"i":[[0,0],[0,0]],"o":[[0,0],[0,0]],"v":[[100,51],[28,51]],"c":false}]},{"i":{"x":0.2,"y":1},"o":{"x":0.8,"y":0},"t":25,"s":[{"i":[[0,0],[0,0]],"o":[[0,0],[0,0]],"v":[[110,51.125],[18,51.125]],"c":false}]},{"t":48,"s":[{"i":[[0,0],[0,0]],"o":[[0,0],[0,0]],"v":[[100,51],[28,51]],"c":false}]}],"ix":2},"nm":"Path 1","mn":"ADBE Vector Shape - Group","hd":false},{"ty":"st","c":{"a":0,"k":[0,0,0,1],"ix":3},"o":{"a":0,"k":100,"ix":4},"w":{"a":0,"k":5,"ix":5},"lc":2,"lj":2,"bm":0,"nm":"Stroke 1","mn":"ADBE Vector Graphic - Stroke","hd":false},{"ty":"tr","p":{"a":0,"k":[0,0],"ix":2},"a":{"a":0,"k":[0,0],"ix":1},"s":{"a":0,"k":[100,100],"ix":3},"r":{"a":0,"k":0,"ix":6},"o":{"a":0,"k":100,"ix":7},"sk":{"a":0,"k":0,"ix":4},"sa":{"a":0,"k":0,"ix":5},"nm":"Transform"}],"nm":"Group 3","np":2,"cix":2,"bm":0,"ix":3,"mn":"ADBE Vector Group","hd":false},{"ty":"gr","it":[{"ind":0,"ty":"sh","ix":1,"ks":{"a":1,"k":[{"i":{"x":0.2,"y":1},"o":{"x":0.8,"y":0},"t":9,"s":[{"i":[[0,0],[0,0]],"o":[[0,0],[0,0]],"v":[[51,28],[51,100]],"c":false}]},{"i":{"x":0.2,"y":1},"o":{"x":0.8,"y":0},"t":25,"s":[{"i":[[0,0],[0,0]],"o":[[0,0],[0,0]],"v":[[51.125,17.688],[51.125,110.625]],"c":false}]},{"t":48,"s":[{"i":[[0,0],[0,0]],"o":[[0,0],[0,0]],"v":[[51,28],[51,100]],"c":false}]}],"ix":2},"nm":"Path 1","mn":"ADBE Vector Shape - Group","hd":false},{"ty":"st","c":{"a":0,"k":[0,0,0,1],"ix":3},"o":{"a":0,"k":100,"ix":4},"w":{"a":0,"k":5,"ix":5},"lc":2,"lj":2,"bm":0,"nm":"Stroke 1","mn":"ADBE Vector Graphic - Stroke","hd":false},{"ty":"tr","p":{"a":0,"k":[0,0],"ix":2},"a":{"a":0,"k":[0,0],"ix":1},"s":{"a":0,"k":[100,100],"ix":3},"r":{"a":0,"k":0,"ix":6},"o":{"a":0,"k":100,"ix":7},"sk":{"a":0,"k":0,"ix":4},"sa":{"a":0,"k":0,"ix":5},"nm":"Transform"}],"nm":"Group 4","np":2,"cix":2,"bm":0,"ix":4,"mn":"ADBE Vector Group","hd":false}],"ip":0,"op":241,"st":0,"bm":0}],"markers":[]}